alerts_in_ua/__init__.py
alerts_in_ua/alerts_client.py
alerts_in_ua/async_alerts_client.py
alerts_in_ua/base_alerts_client.py
alerts_in_ua/exceptions.py
alerts_in_ua/location.py
alerts_in_ua/locations.py
alerts_in_ua/map_style.py
alerts_in_ua/resources/map/Ukraine full.svg
alerts_in_ua/resources/map/Ukraine simple.svg
alerts_in_ua/resources/map/Ukraine.svg
alerts_in_ua_py-1.4.4.dist-info/licenses/LICENSE
alerts_in_ua_py-1.4.4.dist-info/METADATA
alerts_in_ua_py-1.4.4.dist-info/WHEEL
alerts_in_ua_py-1.4.4.dist-info/top_level.txt
alerts_in_ua_py-1.4.4.dist-info/RECORD
