Metadata-Version: 2.4
Name: alerts_in_ua.py
Version: 1.4.4
Summary: Бібліотека для використання API сайту alerts.in.ua
Home-page: https://github.com/FOUREX/alerts_in_ua.py
Author: FOUREX, SladkayaDoza
Author-email: Foxtrotserega@gmail.com
License: MIT
License-File: LICENSE
Requires-Dist: aiohttp~=3.8.3
Requires-Dist: requests~=2.32.5
Requires-Dist: svglib~=1.5.1
Requires-Dist: reportlab~=3.6.12
Dynamic: author
Dynamic: author-email
Dynamic: description
Dynamic: description-content-type
Dynamic: home-page
Dynamic: license
Dynamic: license-file
Dynamic: requires-dist
Dynamic: summary
